valenceai/__init__.py
valenceai/client.py
valenceai/config.py
valenceai/exceptions.py
valenceai/logger.py
valenceai/long_audio.py
valenceai/short_audio.py
valenceai-0.5.1.dist-info/METADATA
valenceai-0.5.1.dist-info/WHEEL
valenceai-0.5.1.dist-info/top_level.txt
valenceai-0.5.1.dist-info/RECORD
