Metadata-Version: 2.4
Name: valenceai
Version: 0.5.1
Summary: Python SDK for Valence Vibrations Emotion Detection API
Author-email: Valence Dev Team <shannon@valencevibrations.com>
Requires-Python: >=3.8
Requires-Dist: requests
Requires-Dist: tqdm
